{
  "swagger": "2.0",
  "info": {
    "title": "Echo API",
    "description": "Echo API",
    "version": "1.0",
    "contact": {
      "name": "DataTrails",
      "url": "https://www.datatrails.ai"
    }
  },
  "tags": [],
  "basePath": "/archivist/v1/echo",
  "schemes": [
    "https"
  ],
  "consumes": [
    "application/json"
  ],
  "produces": [
    "application/json"
  ],
  "paths": {
    "/": {
      "post": {
        "summary": "Echo a message",
        "description": "Echo a message.",
        "operationId": "Echo_Echo",
        "responses": {
          "200": {
            "description": "A successful response.",
            "schema": {
              "$ref": "#/definitions/archivistv1Response"
            }
          },
          "401": {
            "description": "Returned when the user is not authenticated to the system."
          }
        },
        "parameters": [
          {
            "name": "body",
            "description": "TODO: add description  here ",
            "in": "body",
            "required": true,
            "schema": {
              "$ref": "#/definitions/v1Request"
            }
          }
        ],
        "tags": [
          "Echo"
        ]
      }
    }
  },
  "definitions": {
    "archivistv1Response": {
      "type": "object",
      "example": {
        "message": "abcd"
      },
      "properties": {
        "message": {
          "type": "string",
          "description": "TODO: add description  here ",
          "maxLength": 1024
        }
      },
      "description": "TODO: add description  here "
    },
    "v1Request": {
      "type": "object",
      "example": {
        "message": "abcd"
      },
      "properties": {
        "message": {
          "type": "string",
          "description": "TODO: add description  here ",
          "maxLength": 1024
        }
      },
      "description": "TODO: add description  here "
    }
  }
}
